<?xml version="1.0" encoding="utf-8"?>
<odoo>

    <record id="view_consolidation_consolidate_form" model="ir.ui.view">
        <field name="name">account.consolidation.consolidate.form</field>
        <field name="model">account.consolidation.consolidate</field>
        <field name="arch" type="xml">
            <form string="Consolidation: Consolidate">
                <p string="Run the Year-To-Date consolidation until the selected period for the defined subsidiaries."/>
                <p>Balance sheet accounts are consolidated using standard currency rates.</p>
                <p>Profit and Loss accounts are consolidated using monthly currency rates.</p>
                <group>
                    <field name="company_id" />
                    <field name="year" />
                    <field name="month" />
                    <field name="journal_id" domain="[('company_id', '=', company_id)]"/>
                    <field name="target_move"/>
                    <field name="consolidation_profile_ids" />
                </group>
                <footer>
                    <button name="run_consolidation"
                        string="Consolidate"
                        type="object"
                        class="oe_highlight"/>
                    <button string="Cancel" class="oe_link" special="cancel"/>
                </footer>
            </form>
        </field>
    </record>

    <record id="action_consolidation_consolidate" model="ir.actions.act_window">
        <field name="name">Consolidation: Consolidate</field>
        <field name="type">ir.actions.act_window</field>
        <field name="res_model">account.consolidation.consolidate</field>
        <field name="view_type">form</field>
        <field name="view_mode">form</field>
        <field name="target">new</field>
    </record>

</odoo>
